{
  "entries": [
    {
      "rank": 1,
      "user_id": "f43824b8-f0b1-7083-5b9b-cd5ebb68ab16",
      "public_id": "114143200813388967",
      "username": "boobs",
      "wager_total": 18343941
    },
    {
      "rank": 2,
      "user_id": "84f82428-70a1-702d-5225-8c5acb9f9922",
      "public_id": "122437375984013318",
      "username": "reynaisqueen",
      "wager_total": 15191000
    },
    {
      "rank": 3,
      "user_id": "64f8c4f8-3051-707f-cdac-0a4b8c2d277d",
      "public_id": "114266939173507075",
      "username": "mrmustache",
      "wager_total": 8384811
    },
    {
      "rank": 4,
      "user_id": "24c814d8-6051-70e0-6eaa-b543be4cfcbd",
      "public_id": "113692119453012977",
      "username": "muta11",
      "wager_total": 2338535
    },
    {
      "rank": 5,
      "user_id": "f408b478-9051-70d7-fc2a-c7f7659f9f8a",
      "public_id": "112199951399915884",
      "username": "gas",
      "wager_total": 1800324
    },
    {
      "rank": 6,
      "user_id": "94188438-7021-700a-b41b-02f2a20a1af7",
      "public_id": "112943041223987964",
      "username": "freedomgambler",
      "wager_total": 641957
    },
    {
      "rank": 7,
      "user_id": "74b8d498-10a1-7017-c9c8-8f1d7e5a5e43",
      "public_id": "113695802450383861",
      "username": "hoodlum",
      "wager_total": 175755
    },
    {
      "rank": 8,
      "user_id": "b4881438-8091-7097-0b6f-a57c0fe9402e",
      "public_id": "115653965525422512",
      "username": "bgmi1774",
      "wager_total": 97559
    },
    {
      "rank": 9,
      "user_id": "6408b458-e041-708d-a10f-585fb681e166",
      "public_id": "117577694098625282",
      "username": "legacyplayz",
      "wager_total": 95690
    },
    {
      "rank": 10,
      "user_id": "24681488-6061-70e5-d0d8-e549b1aa51c0",
      "public_id": "121815173437723320",
      "username": "ethans",
      "wager_total": 68444
    }
  ]
}