{
  "entries": [
    {
      "rank": 1,
      "user_id": "64f8c4f8-3051-707f-cdac-0a4b8c2d277d",
      "public_id": "114266939173507075",
      "username": "mrmustache",
      "wager_total": 8107511
    },
    {
      "rank": 2,
      "user_id": "f43824b8-f0b1-7083-5b9b-cd5ebb68ab16",
      "public_id": "114143200813388967",
      "username": "boobs",
      "wager_total": 5518899
    },
    {
      "rank": 3,
      "user_id": "94188438-7021-700a-b41b-02f2a20a1af7",
      "public_id": "112943041223987964",
      "username": "freedomgambler",
      "wager_total": 641905
    },
    {
      "rank": 4,
      "user_id": "24c814d8-6051-70e0-6eaa-b543be4cfcbd",
      "public_id": "113692119453012977",
      "username": "muta11",
      "wager_total": 580262
    },
    {
      "rank": 5,
      "user_id": "f408b478-9051-70d7-fc2a-c7f7659f9f8a",
      "public_id": "112199951399915884",
      "username": "gas",
      "wager_total": 412239
    },
    {
      "rank": 6,
      "user_id": "74b8d498-10a1-7017-c9c8-8f1d7e5a5e43",
      "public_id": "113695802450383861",
      "username": "hoodlum",
      "wager_total": 159091
    },
    {
      "rank": 7,
      "user_id": "b4881438-8091-7097-0b6f-a57c0fe9402e",
      "public_id": "115653965525422512",
      "username": "bgmi1774",
      "wager_total": 76348
    },
    {
      "rank": 8,
      "user_id": "042834a8-a001-70a2-6789-471ccb449384",
      "public_id": "111926337526173900",
      "username": "larryjones8526",
      "wager_total": 13344
    },
    {
      "rank": 9,
      "user_id": "d4384478-5011-70d8-bb04-938f2e6c9076",
      "public_id": "113331348499993433",
      "username": "itzdarksterop",
      "wager_total": 11900
    },
    {
      "rank": 10,
      "user_id": "74b894d8-5081-702f-8318-3ec049ce2bf9",
      "public_id": "112225144256205195",
      "username": "mclovin69",
      "wager_total": 6275
    }
  ]
}